atlas/__init__.py
atlas/__main__.py
atlas/cache.py
atlas/core.py
atlas/graph_builder.py
atlas/graph_store.py
atlas/insight_engine.py
atlas/project.py
atlas/types.py
atlas/version.py
atlas/visualize.py
atlas/ai/analyzer.py
atlas/ai/knowledge_graph.py
atlas/ai/pipeline.py
atlas/data_sources/arxiv_client.py
atlas/export/__init__.py
atlas/export/report.py
atlas/ingest/__init__.py
atlas/ingest/arxiv.py
atlas/ingest/basic.py
atlas/link/__init__.py
atlas/link/basic.py
atlas/query/__init__.py
atlas/query/api.py
atlas/utils/logging.py
atlas/viz/__init__.py
atlas/viz/pyvis_viz.py
atlas/viz/visualizer.py
atlas_research-1.1.0.dist-info/licenses/LICENSE
atlas_research-1.1.0.dist-info/METADATA
atlas_research-1.1.0.dist-info/WHEEL
atlas_research-1.1.0.dist-info/top_level.txt
atlas_research-1.1.0.dist-info/RECORD
