Metadata-Version: 2.4
Name: atlas-research
Version: 1.1.0
Summary: Atlas — AI-Powered Research Insight Software (SaaS)
Author-email: Han Jeongwoo <jwhan00427@gmail.com>
License: Apache-2.0
Project-URL: Homepage, https://atlas.vercel.app
Project-URL: Repository, https://github.com/engineer0427/Atlas
Project-URL: Documentation, https://pypi.org/project/atlas-research/
Project-URL: LiveDemo, https://atlas.vercel.app (SaaS Demo Dashboard)
Project-URL: Issues, https://github.com/engineer0427/Atlas/issues
Keywords: AI,Research,Insight,Network,Visualization,Knowledge Graph,Machine Learning,SaaS,FastAPI,Next.js
Classifier: Development Status :: 5 - Production/Stable
Classifier: Intended Audience :: Science/Research
Classifier: Topic :: Scientific/Engineering :: Artificial Intelligence
Classifier: Topic :: Software Development :: Libraries :: Application Frameworks
Classifier: Programming Language :: Python :: 3
Classifier: License :: OSI Approved :: Apache Software License
Classifier: Operating System :: OS Independent
Requires-Python: >=3.9
License-File: LICENSE
Requires-Dist: requests>=2.28.0
Requires-Dist: beautifulsoup4>=4.11.0
Requires-Dist: networkx>=3.0
Requires-Dist: pyvis>=0.3.2
Requires-Dist: pydantic>=2.0.0
Requires-Dist: fastapi>=0.110.0
Requires-Dist: uvicorn>=0.27.0
Requires-Dist: python-dotenv>=1.0.0
Requires-Dist: stripe>=5.0.0
Requires-Dist: pandas>=1.5.0
Requires-Dist: matplotlib>=3.7.0
Requires-Dist: scikit-learn>=1.3.0
Requires-Dist: rich>=13.7.0
Dynamic: license-file
